etl/__init__.py
etl/etl.py
torchetl/__init__.py
torchetl/etl.py
torchetl/base/__init__.py
torchetl/base/dataset.py
torchetl-0.3.9.dist-info/LICENSE
torchetl-0.3.9.dist-info/METADATA
torchetl-0.3.9.dist-info/WHEEL
torchetl-0.3.9.dist-info/top_level.txt
torchetl-0.3.9.dist-info/RECORD
