Metadata-Version: 2.1
Name: torchetl
Version: 0.3.9
Summary: Efficiently Extract, Transform, and Load your dataset into PyTorch models
Home-page: https://github.com/amajidsinar/torchetl
Author: jedi
Author-email: amajidsinar@gmail.com
License: UNKNOWN
Platform: UNKNOWN
Classifier: Programming Language :: Python :: 3
Classifier: License :: OSI Approved :: MIT License
Classifier: Operating System :: OS Independent
